{
  "id": "100003",
  "personalId": "103",
  "name1": "Eva",
  "name2": "Roth",
  "email": "eva.roth@example.com",
  "ownerId": "5919",
  "ownerIdentifier": "10300100",
  "createdOn": "2020-01-01T12:00:00+0200",
  "lastModifiedOn": "2024-11-01T13:00:00+0100",
  "toType": "SamlSynchronizationPartyTO",
  "memberships": [
    {
      "toType": "SamlSynchronizationMembershipTO",
      "id": "3",
      "ownerIdentifier": "10300100",
      "memberOfStructureIdentifier": "10300100",
      "joinedAt": "2020-01-01T12:00:00+0200",
      "exitedAt": null
    }
  ],
  "roles": [
    {
      "toType": "SamlSynchronizationRoleAssignmentTO",
      "id": "3",
      "ownerIdentifier": "10300000",
      "tags": null,
      "roleId": "7555237",
      "delegatedByOrganizationIdentifier": null
    }
  ],
  "achievements": [],
  "formValues": {
    "emails": [],
    "phoneNumbers": [],
    "messengers": [],
    "socialMedia": []
  }
}
